reorderalertforims/__init__.py
reorderalertforims-1.0.0.dist-info/LICENSE.txt
reorderalertforims-1.0.0.dist-info/METADATA
reorderalertforims-1.0.0.dist-info/WHEEL
reorderalertforims-1.0.0.dist-info/top_level.txt
reorderalertforims-1.0.0.dist-info/RECORD
